pcmc/__init__.py
pcmc/cli.py
pcmc/core.py
pcmc/static.py
pcmc/utils.py
pcmc-0.1.6.dist-info/LICENSE
pcmc-0.1.6.dist-info/METADATA
pcmc-0.1.6.dist-info/WHEEL
pcmc-0.1.6.dist-info/entry_points.txt
pcmc-0.1.6.dist-info/top_level.txt
pcmc-0.1.6.dist-info/RECORD
