Metadata-Version: 2.1
Name: pcmc
Version: 0.1.6
Summary: CoinMarketCap site data scrapper as Pandas dataframes.
Home-page: https://github.com/havocesp/pcmc
Author: Daniel J. Umpierrez
Author-email: umpierrez@pm.me
License: UNLICENSE
Keywords: api-wrapper coinmarketcap crypto-currencies altcoins altcoin bitcoin exchange data stock finance
Platform: UNKNOWN
Classifier: Development Status :: 5 - Production/Stable
Classifier: License :: OSI Approved
Classifier: Environment :: Console
Classifier: Intended Audience :: Developers
Classifier: Topic :: Office/Business :: Financial :: Investment
Classifier: Programming Language :: Python :: 3.6
Classifier: Programming Language :: Python :: 3.7
Requires-Dist: tabulate
Requires-Dist: pandas
Requires-Dist: bs4
Requires-Dist: py-term
